IO_Model_Builder-1.1.2.dist-info/METADATA
IO_Model_Builder-1.1.2.dist-info/RECORD
IO_Model_Builder-1.1.2.dist-info/WHEEL
IO_Model_Builder-1.1.2.dist-info/top_level.txt
iomb/__init__.py
iomb/calc.py
iomb/demand2dict.py
iomb/dqi.py
iomb/ia.py
iomb/io.py
iomb/matio.py
iomb/model.py
iomb/refmap.py
iomb/sat.py
iomb/util.py
iomb/validation.py
iomb/data/__init__.py
iomb/data/compartment_meta_data.csv
iomb/data/dq_system_exchanges.json
iomb/data/dq_system_processes.json
iomb/data/location_meta_data.csv
iomb/data/unit_meta_data.csv
