Metadata-Version: 2.1
Name: IO-Model-Builder
Version: 1.1.2
Summary: iomb is a package for creating environmentally extended input-output models
Home-page: https://github.com/USEPA/IO-Model-Builder
Author: Michael Srocka (Greendelta), Wesley Ingwersen (US Environmental Protection Agency)
Author-email: ingwersen.wesley@epa.gov
License: CC0 1.0 Universal (CC0 1.0) Public Domain Dedication
Keywords: economic input-output models,supply and use framework,EEIO,life cycle assessment,LCA,USEEIO
Platform: UNKNOWN
Classifier: Development Status :: 5 - Production/Stable
Classifier: Environment :: Console
Classifier: Intended Audience :: Science/Research
Classifier: License :: CC0 1.0 Universal (CC0 1.0) Public Domain Dedication
Classifier: Programming Language :: Python :: 3.5
Classifier: Topic :: Utilities
Requires-Python: >=3
Requires-Dist: numpy
Requires-Dist: pandas (>=0.17)
Requires-Dist: matplotlib
Requires-Dist: flask
